StrawberryFields_gpu-0.10.0.dist-info/DESCRIPTION.rst
StrawberryFields_gpu-0.10.0.dist-info/METADATA
StrawberryFields_gpu-0.10.0.dist-info/RECORD
StrawberryFields_gpu-0.10.0.dist-info/WHEEL
StrawberryFields_gpu-0.10.0.dist-info/metadata.json
StrawberryFields_gpu-0.10.0.dist-info/top_level.txt
strawberryfields/__init__.py
strawberryfields/_version.py
strawberryfields/circuitdrawer.py
strawberryfields/decompositions.py
strawberryfields/engine.py
strawberryfields/ops.py
strawberryfields/parameters.py
strawberryfields/utils.py
strawberryfields/backends/__init__.py
strawberryfields/backends/base.py
strawberryfields/backends/shared_ops.py
strawberryfields/backends/states.py
strawberryfields/backends/data/fock_beamsplitter_factors_10.npz
strawberryfields/backends/data/fock_beamsplitter_factors_15.npz
strawberryfields/backends/data/fock_beamsplitter_factors_20.npz
strawberryfields/backends/data/fock_beamsplitter_factors_25.npz
strawberryfields/backends/data/fock_beamsplitter_factors_30.npz
strawberryfields/backends/data/fock_beamsplitter_factors_5.npz
strawberryfields/backends/fockbackend/__init__.py
strawberryfields/backends/fockbackend/backend.py
strawberryfields/backends/fockbackend/circuit.py
strawberryfields/backends/fockbackend/ops.py
strawberryfields/backends/gaussianbackend/__init__.py
strawberryfields/backends/gaussianbackend/backend.py
strawberryfields/backends/gaussianbackend/gaussiancircuit.py
strawberryfields/backends/gaussianbackend/ops.py
strawberryfields/backends/gaussianbackend/states.py
strawberryfields/backends/tfbackend/__init__.py
strawberryfields/backends/tfbackend/backend.py
strawberryfields/backends/tfbackend/circuit.py
strawberryfields/backends/tfbackend/ops.py
strawberryfields/backends/tfbackend/states.py
