Metadata-Version: 2.0
Name: StrawberryFields-gpu
Version: 0.10.0
Summary: Open source library for continuous-variable quantum computation
Home-page: http://xanadu.ai
Author: Xanadu Inc.
Author-email: nathan@xanadu.ai
License: Apache License 2.0
Platform: UNKNOWN
Classifier: Development Status :: 3 - Alpha
Classifier: Environment :: Console
Classifier: Intended Audience :: Science/Research
Classifier: License :: OSI Approved :: Apache Software License
Classifier: Natural Language :: English
Classifier: Operating System :: POSIX
Classifier: Operating System :: MacOS :: MacOS X
Classifier: Operating System :: POSIX :: Linux
Classifier: Operating System :: Microsoft :: Windows
Classifier: Programming Language :: Python
Classifier: Programming Language :: Python :: 3
Classifier: Programming Language :: Python :: 3.5
Classifier: Programming Language :: Python :: 3.6
Classifier: Programming Language :: Python :: 3 :: Only
Classifier: Topic :: Scientific/Engineering :: Physics
Provides: strawberryfields
Requires-Dist: numpy (>=1.13)
Requires-Dist: scipy (>=1.0.0)
Requires-Dist: networkx (>=2.0)
Requires-Dist: tensorflow-gpu (<1.7,>=1.3.0)
